{
  "#": "53",
  "Name": "Joe Applebaum",
  "Email": "",
  "Email 2": "",
  "Phone": "",
  "Website": "",
  "Calendar Link": "",
  "LinkedIn": "",
  "Opportunity / Offering": "WhatsApp connection",
  "Notes": "Mentioned re: WhatsApp group. Team skeptical: 'He's going to take whatever he can.' But also noted: 'I'm not above going and taking what he did' \u2014 meaning his approach/methods have strategic value even if he's not a trusted partner.",
  "Source": "Team",
  "": "",
  "Company": "",
  "Business Focus": "",
  "List Size": "",
  "Social Reach": "",
  "Service Provided": "",
  "Who You Serve": "",
  "Seeking": "",
  "Offering": "",
  "Signature Programs": "",
  "Niche": "",
  "Status": "",
  "Bio": "",
  "Match Source": "",
  "Match Status": "Not Matched"
}