{
  "name": "Wendy Macdowall",
  "list_size": 2719,
  "offering": "TRN Coaching",
  "content_platforms": {
    "linkedin": "https://www.linkedin.com/in/therelationshipnerd",
    "facebook": "https://www.facebook.com/the.relationship.nerd/",
    "youtube": "https://www.youtube.com/watch?v=0wy1DjaZ15c",
    "apple_podcast": "https://podcasts.apple.com/us/podcast/the-60-day-dare-body-work-brain-work-and-world-work/id1597346416?i=1000744096207"
  },
  "audience_engagement_score": 0.6000000000000001,
  "website": "https://todaysdreamtomorrowsreality.callcast.co/e/a14b3589-81f4-440b-9a9f-01e413f665c0",
  "linkedin": "https://www.linkedin.com/in/therelationshipnerd",
  "_cache_schema_version": 2,
  "what_you_do": "Wendy Macdowall is a relationship coach who shares her journey of self-discovery, resilience, and transformation.",
  "who_you_serve": "Wendy's story and insights are intended to inspire listeners to embrace their own unique journey and the beauty of life's mosaic.",
  "signature_programs": "Wendy offers a 'Find Your Voice' checklist and a free session to schedule a 'Couples Connection Session'.",
  "booking_link": "https://calendly.com/wendy-d-bryant/couples_connection_session",
  "niche": "relationships",
  "tags": [
    "relationship coach",
    "self-discovery",
    "resilience",
    "transformation"
  ],
  "audience_type": "general public",
  "business_focus": "Wendy Macdowall shares her personal journey and offers insights and guidance on navigating relationships and living authentically.",
  "service_provided": "relationship coaching, free session",
  "_crawl4ai_enriched": true,
  "_crawl4ai_timestamp": "2026-02-18T01:36:00.735489"
}