{
  "name": "Family Violence Mindset",
  "company": "Solutions",
  "website": "https://www.facebook.com/thriveafterfamilyviolence",
  "list_size": 838,
  "offering": "Dianne Simboromily, Group Coaching, Membership Platform, Public Speaking, Spiritual Coaching",
  "content_platforms": {
    "youtube": "https://www.youtube.com/watch?v=vg23wyKn7ZM",
    "linkedin": "https://www.linkedin.com/advice/0/what-most-effective-interventions-strategies-working"
  },
  "jv_history": [
    {
      "partner_name": "Facing Internalized Sexism: Women becoming better Allies to women living in abuse and trauma.",
      "format": "endorsement",
      "source_quote": "Friends and Family Ally booklet to help teach the most vital ... are in various stages of alarm and abuse, what victim blaming statements look like and their impacts and how to partner ... What are th",
      "source_url": "https://www.linkedin.com/pulse/facing-internalized-sexism-women-becoming-better-stearns-mandel"
    }
  ],
  "audience_engagement_score": 0.55,
  "_cache_schema_version": 2
}