{
  "name": "Laleh Talebian",
  "company": "Dynamic Natural Advantage",
  "list_size": 3419,
  "content_platforms": {
    "linkedin": "https://www.linkedin.com/in/drlalehphd",
    "youtube": "https://www.youtube.com/watch?v=B2-QCv-hChY"
  },
  "audience_engagement_score": 0.55,
  "website": "https://medium.com/authority-magazine/dr-laleh-talebian-of-dynamic-natural-advantage-wellness-what-you-need-to-know-before-you-consider-5fd47a0ea700",
  "linkedin": "https://www.linkedin.com/in/drlalehphd"
}