{
  "name": "sherry gaba",
  "company": "sherry gaba",
  "list_size": 88900,
  "content_platforms": {
    "apple_podcast": "https://podcasts.apple.com/gb/podcast/better-than-ever-w-sherry-and-larissa/id1502742045",
    "instagram": "https://www.instagram.com/p/DIL2wSUOscy/",
    "youtube": "https://www.youtube.com/watch?v=tgWmIdrOPXg"
  },
  "jv_history": [
    {
      "partner_name": "",
      "format": "endorsement",
      "source_quote": "I interviewed Sherry Gaba, LCSW who is a psychotherapist and love coach special",
      "source_url": "https://podcasts.apple.com/us/podcast/50-love-addiction-codependency-with-sherry-gaba/id1506259735?i=1000511277548"
    }
  ],
  "audience_engagement_score": 0.6000000000000001,
  "website": "https://sherrygaba.com/"
}