{
  "name": "Melva Johnson",
  "company": "Johnsoon Relationship",
  "list_size": 1747,
  "content_platforms": {
    "linkedin": "https://www.linkedin.com/feed/update/urn:li:activity:6530856357124542464",
    "facebook": "https://www.facebook.com/screengemsbyronnie/posts/a-blast-from-the-past-don-johnson-and-melanie-griffith-were-first-married-for-si/1013382074298777/"
  },
  "audience_engagement_score": 0.4,
  "website": "https://soulivity.com/videos/soulivity-today-show/soulivity-today-rediscovering-intimacy-and-passion-in-your-relationship-10-8-2024",
  "linkedin": "https://www.linkedin.com/in/melva-johnson",
  "_cache_schema_version": 2,
  "what_you_do": "Melva Johnson is a noted relationship expert and co-founder of the Johnson Relationship Institute for Couples.",
  "who_you_serve": "Couples facing challenges in their relationships.",
  "social_proof": "Author of '10 Secrets to a Long-Lasting, Passionate Marriage'",
  "niche": "relationships, intimacy, passion",
  "tags": [
    "relationships",
    "intimacy",
    "passion"
  ],
  "audience_type": "B2C",
  "business_focus": "Providing expert relationship advice and strategies to help couples rekindle love, intimacy, and passion.",
  "service_provided": "Relationship counseling, workshops, books",
  "_crawl4ai_enriched": true,
  "_crawl4ai_timestamp": "2026-02-18T01:41:14.570530"
}