{
  "name": "Hillary Black",
  "company": "Hillary Black Enterprises Inc",
  "list_size": 2013,
  "offering": "Business Coaching, Business Consulting, Communication Training, Intuition Coaching, Joint Venture Resources, Online Education for Business Owners, Speaker Promotion, Speaking Opportunities, Spiritual Coaching",
  "content_platforms": {
    "linkedin": "https://www.linkedin.com/company/hillary-black",
    "instagram": "https://www.instagram.com/reel/DCoG6koNPt7/?hl=en"
  },
  "jv_history": [
    {
      "partner_name": "Hillary Black, MSW, CEC | Executive Coach | Mom to Samuel & Blyer",
      "format": "endorsement",
      "source_quote": "Talent at Cheil Agency Network \n\nNew York, New York, United States (US) ... ### Joint CEO Talent Acquisition Executive Recruitment at Kay & Black, Talent Management ... Founded Kay & Black's coaching ",
      "source_url": "https://www.linkedin.com/in/hillaryfblack"
    }
  ],
  "audience_engagement_score": 0.4,
  "website": "https://www.hillary.black/about"
}