{
  "name": "Susan Shatzer",
  "company": "Susan Shatzer International",
  "list_size": 28927,
  "offering": "Business Coaching, Business Consulting, Communication Training, Group Coaching, Intuition Coaching, Podcast Host, Spiritual Coaching",
  "content_platforms": {
    "linkedin": "https://www.linkedin.com/posts/susanshatzer_does-this-movie-resonate-with-you-do-you-activity-7221947280168206336-fL79",
    "facebook": "https://www.facebook.com/susan.zatz/"
  },
  "jv_history": [
    {
      "partner_name": "How \"The Frequency of Miracles\" explores miracles",
      "format": "endorsement",
      "source_quote": "Energetic Empowerment Expert ~ I clear any limiting beliefs you may have while eliminating past trauma so ... Does this movie resonate with you? Do you recognize any of the men and women featured in t",
      "source_url": "https://www.linkedin.com/posts/susanshatzer_does-this-movie-resonate-with-you-do-you-activity-7221947280168206336-fL79"
    }
  ],
  "audience_engagement_score": 0.4,
  "linkedin": "https://www.linkedin.com/in/susanshatzer"
}