{
  "name": "Amelia South",
  "list_size": 0,
  "what_you_do": "Executive coaching for CEO and executive moms, helping them reclaim time, delegate effectively, and lead with confidence at work and home.",
  "business_focus": "Executive and leadership coaching for CEO and executive moms to reclaim time, delegate, and lead confidently.",
  "content_platforms": {
    "linkedin": "https://www.linkedin.com/in/amelia-south-ct",
    "facebook": "https://www.facebook.com/nobsherbalist/",
    "apple_podcast": "https://podcasts.apple.com/ng/podcast/black-birch-with-amelia-south-tummy-ache-tea/id1570551691?i=1000674988386",
    "youtube": "https://www.youtube.com/user/itsameliax"
  },
  "audience_engagement_score": 0.6000000000000001,
  "website": "https://coachamelia.com/",
  "_cache_schema_version": 2,
  "_phase2_enriched": true,
  "_phase2_date": "2026-02-18T07:00:57.993186",
  "who_you_serve": "CEO and executive moms.",
  "niche": "Executive coaching",
  "bio": "Amelia is an executive coach based in San Diego, CA, dedicated to professional coaching since 2007. She specializes in coaching CEO and executive moms to lead with less stress and more clarity. Unlike many executives who turn to coaching as a second act, Amelia has been committed to coaching as her primary career.",
  "tags": [
    "executive coaching",
    "leadership coaching",
    "leadership training",
    "delegation",
    "work-life balance",
    "executive moms"
  ],
  "audience_type": "Corporate",
  "service_provided": "Executive coaching, leadership coaching, leadership training, EMMPOWER cohort program, strategy calls",
  "network_role": "Educator",
  "signature_programs": "EMMPOWER Cohort, The Mastery Path"
}