{
  "name": "Sue London",
  "company": "7 Dogs Media",
  "list_size": 15084,
  "offering": "Business Coaching, Children and Family, Intuition Coaching, Podcast Host, Public Speaking, Spiritual Coaching",
  "content_platforms": {
    "facebook": "https://www.facebook.com/suelondon2/",
    "linkedin": "https://www.linkedin.com/posts/suethompsonuk_graphicdesign-stokesley-activity-6866427520913354752-FQXk",
    "youtube": "https://www.youtube.com/@suedodge2674"
  },
  "jv_history": [
    {
      "partner_name": "Greater London Enterprise Awards - Winners List (2023) - SME News | Sue Laidlaw",
      "format": "endorsement",
      "source_quote": "law\u2019s Post\n\n Sue Laidlaw Founder and Senior Partner of Laidlaw Group LLP and Co-Founder and Chair of Board- Sponsorstars\n\n2y ... Passionate and experienced Marketing Recruiter with 20 years experience",
      "source_url": "https://www.linkedin.com/posts/sue-laidlaw-83ba9117_greater-london-enterprise-awards-winners-activity-7103316229238439937-gkOV"
    }
  ],
  "audience_engagement_score": 0.6000000000000001,
  "website": "https://asksuelondon.com/",
  "linkedin": "https://ca.linkedin.com/in/asksuelondon",
  "_cache_schema_version": 2,
  "what_you_do": "Provides healing, guidance, and spiritual connection for people and their beloved pets.",
  "who_you_serve": "People and their pets seeking healing, transformation, and spiritual connection.",
  "social_proof": "Award-winning Top Hospice Pet Doula, People & Pet Healer, and distinguished Empowered Woman and Humanitarian.",
  "signature_programs": "Membership Program, Personalized Consultation, Reiki Training, eBooks, Songs, and Gift Vouchers.",
  "booking_link": "https://asksuelondon.com/personalized-consultation",
  "niche": "spiritual healing, pet healing",
  "tags": [
    "healing",
    "spiritual connection",
    "pet healing",
    "transformation"
  ],
  "audience_type": "B2C",
  "business_focus": "Providing healing, guidance, and spiritual connection for people and their beloved pets.",
  "service_provided": "Personalized Consultation, Reiki Training, eBooks, Songs, Gift Vouchers",
  "_crawl4ai_enriched": true,
  "_crawl4ai_timestamp": "2026-02-18T01:09:16.512114"
}