{
  "name": "Krystalya Marie'",
  "company": "Empowered Spirit, Inc.",
  "list_size": 12100,
  "content_platforms": {
    "linkedin": "https://www.linkedin.com/in/krystalya",
    "instagram": "https://www.instagram.com/krystal.love.crystals/p/CJ47at-B5E6/",
    "youtube": "https://www.youtube.com/watch?v=-NW2q0UfXVs",
    "facebook": "https://www.facebook.com/theecrystalbar/posts/1409337636743022/",
    "apple_podcast": "https://podcasts.apple.com/gb/podcast/lady-krystianna-on-psychic-energy-healing-and/id1551928221?i=1000548817501"
  },
  "audience_engagement_score": 0.65,
  "website": "https://empoweredspirit.com/",
  "linkedin": "https://www.linkedin.com/in/krystalya",
  "_cache_schema_version": 2,
  "what_you_do": "Empowered Spirit provides a body, mind, spirit approach for total health using Krystagraphs (Empowerment Symbols/colored images) to help people overcome health and emotional challenges.",
  "who_you_serve": "People looking to achieve optimum health, peak performance energy, and overcome the effects of jet lag.",
  "signature_programs": "Krystagraphs, Self-Love Bundle, Audio Programs, Healing Kits, Books & Card Decks",
  "niche": "energy healing, alternative health",
  "tags": [
    "energy healing",
    "alternative health",
    "krystagraphs"
  ],
  "audience_type": "B2C",
  "business_focus": "Providing a body, mind, spirit approach for total health using Krystagraphs (Empowerment Symbols/colored images).",
  "service_provided": "Krystagraphs, audio programs, healing kits, books, card decks, private sessions",
  "_crawl4ai_enriched": true,
  "_crawl4ai_timestamp": "2026-02-18T01:12:08.694913"
}