{
  "name": "Bertramedia LLC  & Good Ship",
  "company": "Happens LLC",
  "list_size": 0,
  "content_platforms": {
    "linkedin": "https://www.linkedin.com/in/cindybertram",
    "spotify_podcast": "https://open.spotify.com/episode/4zlWbsPDcq8hEsV4xampJO"
  },
  "jv_history": [
    {
      "partner_name": "Life is Good in New Hampshire",
      "format": "endorsement",
      "source_quote": "Hassell, President, Bert Jacobs, CEO/Co Founder, and Keith Campbell, VP, ... Brothers John and Bert Jacobs started selling their custom designed T-shirts on the streets of Boston in 1989.\u00a0Their ... Li",
      "source_url": "https://www.linkedin.com/pulse/life-good-new-hampshire-michael-bergeron"
    },
    {
      "partner_name": "That text is a scam - Today, Explained | Podcast on Spotify",
      "format": "podcast_guest",
      "source_quote": "an easy remote job? We find out how they work, why they're so ubiquitous, ... you!Learn more about sponsor message choices: podcastchoices.com/adchoicesNPR Privacy Policy Nov 25, 2025\n\n18 min 54 sec\n\n",
      "source_url": "https://open.spotify.com/episode/4zlWbsPDcq8hEsV4xampJO"
    }
  ],
  "website": "https://www.bertamedina.com/"
}