{
  "name": "Sarah Lascano",
  "company": "RayZen Energy",
  "list_size": 1200,
  "content_platforms": {
    "linkedin": "https://www.linkedin.com/in/sarah-pikos-85476ba",
    "apple_podcast": "https://podcasts.apple.com/us/podcast/finally-free-podcast/id1552555920",
    "youtube": "https://www.youtube.com/watch?v=H6VkSIrEzg4"
  },
  "jv_history": [
    {
      "partner_name": "ZEN has just finalised a significant agreement to decarbonise one of the country's major industrial ",
      "format": "endorsement",
      "source_quote": "with ACEN Australia, we\u00a0will supply clean energy to BOC, the leading supplier of industrial gases in ... #ZENEnergy #Partnerships #ThisIsTransition \n https://lnkd.in/gYnM4MVs NSW solar farm to supply ",
      "source_url": "https://www.linkedin.com/posts/paul-sheridan-27166519_nsw-solar-farm-to-supply-almost-half-energy-activity-7316193790543777792-m7L9"
    }
  ],
  "audience_engagement_score": 0.55
}